fds/__init__.py
fds/sdk/__init__.py
fds/sdk/FactSetEstimatesReportBuilder/__init__.py
fds/sdk/FactSetEstimatesReportBuilder/api_client.py
fds/sdk/FactSetEstimatesReportBuilder/configuration.py
fds/sdk/FactSetEstimatesReportBuilder/exceptions.py
fds/sdk/FactSetEstimatesReportBuilder/model_utils.py
fds/sdk/FactSetEstimatesReportBuilder/rest.py
fds/sdk/FactSetEstimatesReportBuilder/api/__init__.py
fds/sdk/FactSetEstimatesReportBuilder/api/all_estimates_api.py
fds/sdk/FactSetEstimatesReportBuilder/api/estimate_tables_api.py
fds/sdk/FactSetEstimatesReportBuilder/apis/__init__.py
fds/sdk/FactSetEstimatesReportBuilder/model/__init__.py
fds/sdk/FactSetEstimatesReportBuilder/model/error_object.py
fds/sdk/FactSetEstimatesReportBuilder/model/error_object_links.py
fds/sdk/FactSetEstimatesReportBuilder/model/error_object_source.py
fds/sdk/FactSetEstimatesReportBuilder/model/error_response.py
fds/sdk/FactSetEstimatesReportBuilder/model/meta.py
fds/sdk/FactSetEstimatesReportBuilder/model/response.py
fds/sdk/FactSetEstimatesReportBuilder/models/__init__.py
fds.sdk.FactSetEstimatesReportBuilder-1.0.14.dist-info/LICENSE
fds.sdk.FactSetEstimatesReportBuilder-1.0.14.dist-info/METADATA
fds.sdk.FactSetEstimatesReportBuilder-1.0.14.dist-info/WHEEL
fds.sdk.FactSetEstimatesReportBuilder-1.0.14.dist-info/top_level.txt
fds.sdk.FactSetEstimatesReportBuilder-1.0.14.dist-info/RECORD
